src/traffic_light.v
module traffic_light(
    input clk,
    input reset,
    output reg [1:0] ns_light,
    output reg [1:0] ew_light
);

reg [1:0] state;

parameter S0 = 2'b00;
parameter S1 = 2'b01;
parameter S2 = 2'b10;
parameter S3 = 2'b11;

parameter GREEN  = 2'b00;
parameter YELLOW = 2'b01;
parameter RED    = 2'b10;

always @(posedge clk or posedge reset)
begin
    if(reset)
        state <= S0;
    else
    begin
        case(state)
            S0: state <= S1;
            S1: state <= S2;
            S2: state <= S3;
            S3: state <= S0;
            default: state <= S0;
        endcase
    end
end

always @(*)
begin
    case(state)

        S0:
        begin
            ns_light = GREEN;
            ew_light = RED;
        end

        S1:
        begin
            ns_light = YELLOW;
            ew_light = RED;
        end

        S2:
        begin
            ns_light = RED;
            ew_light = GREEN;
        end

        S3:
        begin
            ns_light = RED;
            ew_light = YELLOW;
        end

        default:
        begin
            ns_light = RED;
            ew_light = RED;
        end

    endcase
end

endmodule

tb/traffic_light_tb.v
`timescale 1ns/1ps

module traffic_light_tb;

reg clk;
reg reset;

wire [1:0] ns_light;
wire [1:0] ew_light;

traffic_light uut(
    .clk(clk),
    .reset(reset),
    .ns_light(ns_light),
    .ew_light(ew_light)
);

always
begin
    #5 clk = ~clk;
end

initial
begin
    clk = 0;
    reset = 1;

    #10 reset = 0;

    #80;

    $finish;
end

initial
begin
    $dumpfile("traffic_light.vcd");
    $dumpvars(0, traffic_light_tb);
end

endmodule

traffic_light.vcd
$date
	Fri Jun 12 17:53:39 2026
$end
$version
	Icarus Verilog
$end
$timescale
	1ps
$end
$scope module traffic_light_tb $end
$var wire 2 ! ns_light [1:0] $end
$var wire 2 " ew_light [1:0] $end
$var reg 1 # clk $end
$var reg 1 $ reset $end
$scope module uut $end
$var wire 1 # clk $end
$var wire 1 $ reset $end
$var parameter 2 % GREEN $end
$var parameter 2 & RED $end
$var parameter 2 ' S0 $end
$var parameter 2 ( S1 $end
$var parameter 2 ) S2 $end
$var parameter 2 * S3 $end
$var parameter 2 + YELLOW $end
$var reg 2 , ew_light [1:0] $end
$var reg 2 - ns_light [1:0] $end
$var reg 2 . state [1:0] $end
$upscope $end
$upscope $end
$enddefinitions $end
$comment Show the parameter values. $end
$dumpall
b1 +
b11 *
b10 )
b1 (
b0 '
b10 &
b0 %
$end
#0
$dumpvars
b0 .
b0 -
b10 ,
1$
0#
b10 "
b0 !
$end
#5000
1#
#10000
0#
0$
#15000
b1 !
b1 -
b1 .
1#
#20000
0#
#25000
b0 "
b0 ,
b10 !
b10 -
b10 .
1#
#30000
0#
#35000
b1 "
b1 ,
b11 .
1#
#40000
0#
#45000
b10 "
b10 ,
b0 !
b0 -
b0 .
1#
#50000
0#
#55000
b1 !
b1 -
b1 .
1#
#60000
0#
#65000
b0 "
b0 ,
b10 !
b10 -
b10 .
1#
#70000
0#
#75000
b1 "
b1 ,
b11 .
1#
#80000
0#
#85000
b10 "
b10 ,
b0 !
b0 -
b0 .
1#
